{
  "project_info": {
    "project_number": "709871254298",
    "firebase_url": "https://kuber-544b9.firebaseio.com",
    "project_id": "kuber-544b9",
    "storage_bucket": "kuber-544b9.appspot.com"
  },
  "client": [
    {
      "client_info": {
        "mobilesdk_app_id": "1:709871254298:android:b39b2d03b8fde733",
        "android_client_info": {
          "package_name": "svkt.wallet"
        }
      },
      "oauth_client": [
        {
          "client_id": "709871254298-vv4tsu2j1gof3s6n41f62fs6u30vfuh4.apps.googleusercontent.com",
          "client_type": 3
        }
      ],
      "api_key": [
        {
          "current_key": "AIzaSyBxkDskN2960amblaqOGm6oUBc2MYwqImk"
        }
      ],
      "services": {
        "analytics_service": {
          "status": 1
        },
        "appinvite_service": {
          "status": 1,
          "other_platform_oauth_client": []
        },
        "ads_service": {
          "status": 2
        }
      }
    }
  ],
  "configuration_version": "1"
}